nuggan/__init__.py
nuggan/id_maker.py
nuggan-0.2.0.dist-info/LICENSE
nuggan-0.2.0.dist-info/WHEEL
nuggan-0.2.0.dist-info/METADATA
nuggan-0.2.0.dist-info/RECORD
