Metadata-Version: 2.1
Name: nuggan
Version: 0.2.0
Summary: A library for creating self-aware ids
Home-page: https://github.com/kjschiroo/nuggan
License: MIT
Author: Kevin Schiroo
Author-email: kjschiroo@gmail.com
Requires-Python: >=3.6,<4.0
Classifier: License :: OSI Approved :: MIT License
Classifier: Programming Language :: Python :: 3
Classifier: Programming Language :: Python :: 3.6
Classifier: Programming Language :: Python :: 3.7
Project-URL: Repository, https://github.com/kjschiroo/nuggan
